.gitignore
.python-version
Dockerfile
MANIFEST.in
Makefile
README.md
requirements.txt
setup.py
.github/workflows/pythonpackage.yml
api/__init__.py
api/api.py
notebooks/.keep
notebooks/VGG16.ipynb
notebooks/playground.ipynb
projectYoda/__init__.py
projectYoda/data.py
projectYoda/gcp.py
projectYoda/params.py
projectYoda/trainer.py
projectYoda.egg-info/PKG-INFO
projectYoda.egg-info/SOURCES.txt
projectYoda.egg-info/dependency_links.txt
projectYoda.egg-info/not-zip-safe
projectYoda.egg-info/requires.txt
projectYoda.egg-info/top_level.txt
projectYoda/data/.keep
scripts/Project-YODA-run
tests/__init__.py